theonerig/__init__.py
theonerig/_modidx.py
theonerig/_nbdev.py
theonerig/core.py
theonerig/database.py
theonerig/eyetrack.py
theonerig/leddome.py
theonerig/modelling.py
theonerig/plotting.py
theonerig/processing.py
theonerig/testdata.py
theonerig/utils.py
theonerig/synchro/__init__.py
theonerig/synchro/extracting.py
theonerig/synchro/io.py
theonerig/synchro/nested_stims.py
theonerig/synchro/processing.py
theonerig-1.0.2.dist-info/LICENSE
theonerig-1.0.2.dist-info/METADATA
theonerig-1.0.2.dist-info/WHEEL
theonerig-1.0.2.dist-info/top_level.txt
theonerig-1.0.2.dist-info/RECORD
