Metadata-Version: 2.1
Name: theonerig
Version: 1.0.2
Summary: Timeseries synchronisation toolkit for computational neuroscience
Home-page: https://github.com/Tom-TBT/theonerig
Author: Tom Boissonnet
Author-email: tom.boissonnet@hotmail.fr
License: Apache Software License 2.0
Keywords: neuroscience synchronisation timeserie pipeline
Classifier: Development Status :: 3 - Alpha
Classifier: Intended Audience :: Developers
Classifier: License :: OSI Approved :: Apache Software License
Classifier: Natural Language :: English
Classifier: Programming Language :: Python :: 3.9
Requires-Python: >=3.9
License-File: LICENSE
Requires-Dist: numpy
Requires-Dist: matplotlib
Requires-Dist: scipy
Requires-Dist: h5py
Requires-Dist: scikit-learn
Requires-Dist: pandas
Requires-Dist: seaborn
Requires-Dist: sqlalchemy
Requires-Dist: colorama
Requires-Dist: tqdm
Requires-Dist: mysql-connector-python
Requires-Dist: jupyterlab
Requires-Dist: nbdev
Requires-Dist: mysqlclient
